{
    "attribution": "新編 日本古典文学全集",
    "label": [
        "るべき",
        "て、その木のもとは立ちてかへるに日暮になりぬ。御供な",
        "人、酒をもたせて、野よりいで来たり。この酒を飲みてむ",
        "て、よき所を求めゆくに、天の河といふ所にいたりぬ。親",
        "に馬の頭、大御酒まゐる。親王ののたまひける、「交野を",
        "りて、天の河のほとりにいたる、を題にて、歌よみて盃は",
        "せ」とのたまうければ、かの馬の頭よみて奉りける。",
        "狩りくらしたなばたつめに宿からむ天の河原にわれは来",
        "にけり",
        "王、歌をかへすがへす誦じたまうて、返しえしたまはず。",
        "の有常、御供に仕うまつれり。それが返し、",
        "ひととせにひとたび来ます君待てば宿かす人もあらじと",
        "ぞ思ふ",
        "へりて宮に入らせたまひぬ。夜ふくるまで酒飲み、物語し",
        "、あるじの親王、酔ひて入りたまひなむとす。十一日の月"
    ],
    "objectID": "00185",
    "page": 185,
    "related": {
        "ndl_1288457": [
            {
                "canvas": "https://www.dl.ndl.go.jp/api/iiif/1287963/canvas/44",
                "curation": 1,
                "image": "https://www.dl.ndl.go.jp/api/iiif/1287963/F0000044/full/full/0/default.jpg",
                "manifest": "https://www.dl.ndl.go.jp/api/iiif/1287963/manifest.json",
                "page": 44,
                "type": "コマ"
            },
            {
                "canvas": "https://www.dl.ndl.go.jp/api/iiif/1287963/canvas/45",
                "curation": 1,
                "image": "https://www.dl.ndl.go.jp/api/iiif/1287963/F0000045/full/full/0/default.jpg",
                "manifest": "https://www.dl.ndl.go.jp/api/iiif/1287963/manifest.json",
                "page": 45,
                "type": "コマ"
            }
        ]
    },
    "target": "ise",
    "text": "るべき\nて、その木のもとは立ちてかへるに日暮になりぬ。御供な\n人、酒をもたせて、野よりいで来たり。この酒を飲みてむ\nて、よき所を求めゆくに、天の河といふ所にいたりぬ。親\nに馬の頭、大御酒まゐる。親王ののたまひける、「交野を\nりて、天の河のほとりにいたる、を題にて、歌よみて盃は\nせ」とのたまうければ、かの馬の頭よみて奉りける。\n狩りくらしたなばたつめに宿からむ天の河原にわれは来\nにけり\n王、歌をかへすがへす誦じたまうて、返しえしたまはず。\nの有常、御供に仕うまつれり。それが返し、\nひととせにひとたび来ます君待てば宿かす人もあらじと\nぞ思ふ\nへりて宮に入らせたまひぬ。夜ふくるまで酒飲み、物語し\n、あるじの親王、酔ひて入りたまひなむとす。十一日の月",
    "type": "ページ",
    "vol": 1,
    "vol_str": "01 伊勢物語"
}