{
    "attribution": "新編 日本古典文学全集",
    "objectID": "00199",
    "page": 199,
    "related": {
        "ndl_1288457": [
            {
                "canvas": "https://www.dl.ndl.go.jp/api/iiif/1287963/canvas/2",
                "curation": 1,
                "image": "https://www.dl.ndl.go.jp/api/iiif/1287963/F0000002/full/full/0/default.jpg",
                "manifest": "https://www.dl.ndl.go.jp/api/iiif/1287963/manifest.json",
                "page": 2,
                "type": "コマ"
            },
            {
                "canvas": "https://www.dl.ndl.go.jp/api/iiif/1287963/canvas/3",
                "curation": 1,
                "image": "https://www.dl.ndl.go.jp/api/iiif/1287963/F0000003/full/full/0/default.jpg",
                "manifest": "https://www.dl.ndl.go.jp/api/iiif/1287963/manifest.json",
                "page": 3,
                "type": "コマ"
            }
        ]
    },
    "target": "ise",
    "type": "ページ",
    "vol": 1,
    "vol_str": "01 伊勢物語"
}