{
    "attribution": "新編 日本古典文学全集",
    "label": [
        "かさむ」といひければ、女、いと忍びて、ものごしにあひ",
        "けり、物語などして、男、",
        "ひこ星に恋はまさりぬ天の河へだつる関をいまはやめて",
        "よ",
        "の歌にめでてあひにけり。",
        "lt;九十六　天の逆手&gt;",
        "むかし、男ありけり。女をとかくいふこと月日経にけり。",
        "木にしあらねば、心苦しとや思ひけむ、やうやうあはれと",
        "ひけり。そのころ、六月の望ばかりなりければ、女、身に",
        "さ一つ二ついできにけり。女いひおこせたる。「いまは何",
        "心もなし。身にかさも一つ二ついでたり。時もいと暑し。",
        "し秋風吹きたちなむ時、かならずあはむ」といへりけり。",
        "まつころほひに、ここかしこより、その人のもとへいなむ",
        "なりとて、口舌いできにけり。さりければ、女の兄、には"
    ],
    "objectID": "00197",
    "page": 197,
    "related": {
        "ndl_1288457": [
            {
                "canvas": "https://www.dl.ndl.go.jp/api/iiif/1287963/canvas/13",
                "curation": 1,
                "image": "https://www.dl.ndl.go.jp/api/iiif/1287963/F0000013/full/full/0/default.jpg",
                "manifest": "https://www.dl.ndl.go.jp/api/iiif/1287963/manifest.json",
                "page": 13,
                "type": "コマ"
            },
            {
                "canvas": "https://www.dl.ndl.go.jp/api/iiif/1287963/canvas/14",
                "curation": 1,
                "image": "https://www.dl.ndl.go.jp/api/iiif/1287963/F0000014/full/full/0/default.jpg",
                "manifest": "https://www.dl.ndl.go.jp/api/iiif/1287963/manifest.json",
                "page": 14,
                "type": "コマ"
            }
        ]
    },
    "target": "ise",
    "text": "かさむ」といひければ、女、いと忍びて、ものごしにあひ\nけり、物語などして、男、\nひこ星に恋はまさりぬ天の河へだつる関をいまはやめて\nよ\nの歌にめでてあひにけり。\nlt;九十六　天の逆手&gt;\nむかし、男ありけり。女をとかくいふこと月日経にけり。\n木にしあらねば、心苦しとや思ひけむ、やうやうあはれと\nひけり。そのころ、六月の望ばかりなりければ、女、身に\nさ一つ二ついできにけり。女いひおこせたる。「いまは何\n心もなし。身にかさも一つ二ついでたり。時もいと暑し。\nし秋風吹きたちなむ時、かならずあはむ」といへりけり。\nまつころほひに、ここかしこより、その人のもとへいなむ\nなりとて、口舌いできにけり。さりければ、女の兄、には",
    "type": "ページ",
    "vol": 1,
    "vol_str": "01 伊勢物語"
}